README.rst
setup.py
manage.py.egg-info/PKG-INFO
manage.py.egg-info/SOURCES.txt
manage.py.egg-info/dependency_links.txt
manage.py.egg-info/entry_points.txt
manage.py.egg-info/top_level.txt
manager/__init__.py
manager/cli.py
manager/main.py
manager/ext/__init__.py
manager/ext/nosetests.py
scripts/manage